tuningtron/__init__.py
tuningtron/tuningtron.py
tuningtron-0.0.44.dist-info/licenses/LICENSE
tuningtron-0.0.44.dist-info/METADATA
tuningtron-0.0.44.dist-info/WHEEL
tuningtron-0.0.44.dist-info/top_level.txt
tuningtron-0.0.44.dist-info/RECORD
