Metadata-Version: 2.4
Name: tuningtron
Version: 0.0.44
Summary: Library for fine-tuning large language models
Author-email: Vladimir Petrukhin <man4j@ya.ru>
Project-URL: Homepage, https://github.com/Equiron-AI/tuningtron
Classifier: Development Status :: 4 - Beta
Classifier: Programming Language :: Python :: 3.11
Classifier: License :: OSI Approved :: MIT License
Classifier: Operating System :: OS Independent
Requires-Python: >=3.11
License-File: LICENSE
Requires-Dist: transformers>=4.56.0
Requires-Dist: datasets>=4.0.0
Requires-Dist: peft>=0.17.1
Requires-Dist: deepspeed==0.17.5
Requires-Dist: sentencepiece>=0.2.1
Requires-Dist: trl>=0.22.1
Requires-Dist: liger-kernel>=0.6.2
Dynamic: license-file
